mensajes/__init__.py
mensajes/adios/despedidas.py
mensajes/hola/__init__.py
mensajes/hola/saludos.py
mensajes_andre-0.0.0.dist-info/licenses/LICENSE
mensajes_andre-0.0.0.dist-info/METADATA
mensajes_andre-0.0.0.dist-info/WHEEL
mensajes_andre-0.0.0.dist-info/top_level.txt
mensajes_andre-0.0.0.dist-info/RECORD
